[
  { "id": "ataque_poderoso",          "name": "Ataque Poderoso",               "name_en": "Power Attack",                "category": "Combate",            "category_en": "Combat",          "type": "cbt",    "prerequisites": "FUE 13, BAB +1",                                                 "prerequisites_en": "STR 13, BAB +1",                                                 "description": "+2 al daño (+3 a dos manos), escala +2 cada 4 BAB. -1 a tiradas de ataque/maniobras (aumenta igual).", "description_en": "+2 to damage (+3 two-handed), scales +2 per 4 BAB. -1 to attack rolls/maneuvers (scales equally)." },
  { "id": "acometer",                 "name": "Acometer",                      "name_en": "Lunge",                       "category": "Combate",            "category_en": "Combat",          "type": "cbt",    "prerequisites": "BAB +6",                                                         "prerequisites_en": "BAB +6",                                                         "description": "+5 pies de alcance cuerpo a cuerpo ese turno. -2 temporal a la CA.", "description_en": "+5 feet of melee reach that turn. -2 temporary AC penalty." },
  { "id": "hendedura",                "name": "Hendedura",                     "name_en": "Cleave",                      "category": "Combate",            "category_en": "Combat",          "type": "cbt",    "prerequisites": "FUE 13, Ataque Poderoso, BAB +1",                                "prerequisites_en": "STR 13, Power Attack, BAB +1",                                   "description": "Ataque extra con BAB completo contra un enemigo adyacente al primer objetivo si el golpe impacta. -2 CA hasta el siguiente turno.", "description_en": "Extra attack at full BAB against an enemy adjacent to the first target if the blow hits. -2 AC until your next turn." },
  { "id": "gran_hendedura",           "name": "Gran Hendedura",                "name_en": "Great Cleave",                "category": "Combate",            "category_en": "Combat",          "type": "cbt",    "prerequisites": "FUE 13, Hendedura, Ataque Poderoso, BAB +4",                     "prerequisites_en": "STR 13, Cleave, Power Attack, BAB +4",                           "description": "Ataques extra encadenados contra todos los adyacentes si se impacta continuamente. -2 CA.", "description_en": "Chained extra attacks against every adjacent foe while you keep hitting. -2 AC." },
  { "id": "hendedura_final",          "name": "Hendedura Final",               "name_en": "Cleaving Finish",             "category": "Combate",            "category_en": "Combat",          "type": "cbt",    "prerequisites": "Hendedura, Gran Hendedura, Ataque Poderoso, BAB +6",             "prerequisites_en": "Cleave, Great Cleave, Power Attack, BAB +6",                     "description": "Permite activar ataques de Hendedura múltiples veces por asalto tras abatir a un enemigo.", "description_en": "Allows triggering Cleave attacks multiple times per round after dropping an enemy." },
  { "id": "doble_tajo",               "name": "Doble Tajo",                    "name_en": "Double Slice",                "category": "Combate",            "category_en": "Combat",          "type": "cbt",    "prerequisites": "DES 15, Combate con dos armas",                                  "prerequisites_en": "DEX 15, Two-Weapon Fighting",                                    "description": "Aplica el 100% del modificador de FUE al daño de la mano torpe (en vez del 50% base).", "description_en": "Apply 100% of your STR modifier to off-hand damage (instead of the base 50%)." },
  { "id": "soltura_arma",             "name": "Soltura con un Arma",           "name_en": "Weapon Focus",                "category": "Combate",            "category_en": "Combat",          "type": "cbt",    "prerequisites": "Competencia con el arma, BAB +1",                                "prerequisites_en": "Weapon proficiency, BAB +1",                                     "description": "+1 permanente a las tiradas de ataque con el arma seleccionada.", "description_en": "Permanent +1 to attack rolls with the chosen weapon." },
  { "id": "soltura_mayor_arma",       "name": "Soltura Mayor con un Arma",     "name_en": "Greater Weapon Focus",        "category": "Combate",            "category_en": "Combat",          "type": "cbt",    "prerequisites": "Soltura con el arma, BAB +1, Guerrero nivel 8",                  "prerequisites_en": "Weapon Focus, BAB +1, Fighter level 8",                          "description": "+1 adicional a las tiradas de ataque con el arma elegida (total +2).", "description_en": "Additional +1 to attack rolls with the chosen weapon (total +2)." },
  { "id": "critico_mejorado",         "name": "Crítico Mejorado",              "name_en": "Improved Critical",           "category": "Combate",            "category_en": "Combat",          "type": "cbt",    "prerequisites": "Competencia con el arma, BAB +8",                                "prerequisites_en": "Weapon proficiency, BAB +8",                                     "description": "Duplica el rango de amenaza de golpe crítico del arma (ej.: 19–20 pasa a 17–20).", "description_en": "Doubles the weapon's critical threat range (e.g., 19-20 becomes 17-20)." },
  { "id": "aplastar",                 "name": "Aplastar",                      "name_en": "Smashing Blow",               "category": "Combate",            "category_en": "Combat",          "type": "cbt",    "prerequisites": "Ataque Poderoso, semiorco",                                      "prerequisites_en": "Power Attack, half-orc",                                         "description": "Ignora los primeros 5 puntos de dureza de objetos. +5 a pruebas de FUE para romper puertas.", "description_en": "Ignores the first 5 points of object hardness. +5 to STR checks to break down doors." },
  { "id": "matanza_pavorosa",         "name": "Matanza Pavorosa",              "name_en": "Dreadful Carnage",            "category": "Combate",            "category_en": "Combat",          "type": "cbt",    "prerequisites": "FUE 15, Ataque Poderoso, Soltura Furiosa, BAB +11",             "prerequisites_en": "STR 15, Power Attack, Furious Focus, BAB +11",                   "description": "Al matar, prueba de Intimidar gratuita contra todos los enemigos a 30 pies.", "description_en": "On a kill, make a free Intimidate check against all enemies within 30 feet." },
  { "id": "golpe_escudo_mejorado",    "name": "Golpe con el Escudo Mejorado",  "name_en": "Improved Shield Bash",        "category": "Combate",            "category_en": "Combat",          "type": "cbt",    "prerequisites": "Competencia con escudos",                                        "prerequisites_en": "Shield Proficiency",                                             "description": "Mantiene el bonificador de CA del escudo al realizar un ataque con él.", "description_en": "Retain the shield's AC bonus when making a shield bash attack." },
  { "id": "especializacion_escudo",   "name": "Especialización con el Escudo", "name_en": "Shield Specialization",       "category": "Combate",            "category_en": "Combat",          "type": "cbt",    "prerequisites": "Nivel de guerrero, Competencia con escudos",                     "prerequisites_en": "Fighter level, Shield Proficiency",                              "description": "+1 a la CA otorgada por el escudo seleccionado.", "description_en": "+1 to the AC granted by the chosen shield." },
  { "id": "disparo_bocajarro",        "name": "Disparo a Bocajarro",           "name_en": "Point-Blank Shot",            "category": "Combate a distancia","category_en": "Ranged Combat",   "type": "cbt",    "prerequisites": "Ninguno",                                                        "prerequisites_en": "None",                                                           "description": "+1 a las tiradas de ataque y daño con armas a distancia contra enemigos a menos de 30 pies.", "description_en": "+1 to attack and damage rolls with ranged weapons against enemies within 30 feet." },
  { "id": "disparo_preciso",          "name": "Disparo Preciso",               "name_en": "Precise Shot",                "category": "Combate a distancia","category_en": "Ranged Combat",   "type": "cbt",    "prerequisites": "Disparo a Bocajarro",                                            "prerequisites_en": "Point-Blank Shot",                                               "description": "Ignora el penalizador de -4 al disparar a enemigos en cuerpo a cuerpo.", "description_en": "Ignore the -4 penalty for shooting into melee." },
  { "id": "disparo_preciso_mejorado", "name": "Disparo Preciso Mejorado",      "name_en": "Improved Precise Shot",       "category": "Combate a distancia","category_en": "Ranged Combat",   "type": "cbt",    "prerequisites": "DES 19, Disparo Preciso, Disparo a Bocajarro, BAB +11",          "prerequisites_en": "DEX 19, Precise Shot, Point-Blank Shot, BAB +11",                "description": "Ignora bonificadores de CA por cobertura y probabilidad de fallo por ocultación (salvo total).", "description_en": "Ignore AC bonuses from cover and miss chance from concealment (except total)." },
  { "id": "disparo_rapido",           "name": "Disparo Rápido",                "name_en": "Rapid Shot",                  "category": "Combate a distancia","category_en": "Ranged Combat",   "type": "cbt",    "prerequisites": "DES 13, Disparo a Bocajarro",                                    "prerequisites_en": "DEX 13, Point-Blank Shot",                                       "description": "Un ataque a distancia extra en un asalto completo. -2 a todas las tiradas de ataque ese asalto.", "description_en": "One extra ranged attack during a full-attack action. -2 to all attack rolls that round." },
  { "id": "disparos_multiples",       "name": "Disparos Múltiples",            "name_en": "Manyshot",                    "category": "Combate a distancia","category_en": "Ranged Combat",   "type": "cbt",    "prerequisites": "DES 17, Disparo Rápido, Disparo a Bocajarro, BAB +6",            "prerequisites_en": "DEX 17, Rapid Shot, Point-Blank Shot, BAB +6",                   "description": "El primer ataque dispara 2 flechas a la vez, aplicando modificadores de daño a ambas.", "description_en": "The first attack fires 2 arrows at once, applying damage modifiers to both." },
  { "id": "disparo_larga_distancia",  "name": "Disparo a Larga Distancia",     "name_en": "Far Shot",                    "category": "Combate a distancia","category_en": "Ranged Combat",   "type": "cbt",    "prerequisites": "Disparo a Bocajarro",                                            "prerequisites_en": "Point-Blank Shot",                                               "description": "Reduce el penalizador por incremento de distancia de -2 a solo -1 por incremento.", "description_en": "Reduces the range increment penalty from -2 to -1 per increment." },
  { "id": "disparo_perforante",       "name": "Disparo Perforante",            "name_en": "Pinpoint Targeting",          "category": "Combate a distancia","category_en": "Ranged Combat",   "type": "cbt",    "prerequisites": "DES 19, Disparo Preciso Mejorado, Disparo a Bocajarro, BAB +16", "prerequisites_en": "DEX 19, Improved Precise Shot, Point-Blank Shot, BAB +16",       "description": "Un ataque estándar que ignora la CA por armadura o escudo. Prohíbe el movimiento ese turno.", "description_en": "Standard action that ignores armor and shield AC. Prevents movement that turn." },
  { "id": "disparo_disruptivo",       "name": "Disparo Disruptivo",            "name_en": "Disruptive Shot",             "category": "Combate a distancia","category_en": "Ranged Combat",   "type": "cbt",    "prerequisites": "DES 13, Disparo a Bocajarro, Guerrero nivel 6",                  "prerequisites_en": "DEX 13, Point-Blank Shot, Fighter level 6",                      "description": "Al impactar a un lanzador de conjuros, su CD de Concentración aumenta en +4.", "description_en": "When you hit a spellcaster, their Concentration DC increases by +4." },
  { "id": "disparar_montura",         "name": "Disparar desde una Montura",    "name_en": "Mounted Archery",             "category": "Combate montado",    "category_en": "Mounted Combat", "type": "cbt",    "prerequisites": "Montar 1 rango, Combatir desde montura",                         "prerequisites_en": "Ride 1 rank, Mounted Combat",                                    "description": "Reduce a la mitad los penalizadores por disparar mientras cabalga.", "description_en": "Halves the penalties for shooting while mounted." },
  { "id": "falsa_apertura",           "name": "Falsa Apertura",                "name_en": "Gang Up / Opening",           "category": "Combate",            "category_en": "Combat",          "type": "cbt",    "prerequisites": "DES 13, Esquiva, Soltura con el arma",                           "prerequisites_en": "DEX 13, Dodge, Weapon Focus",                                    "description": "Provoca ataques de oportunidad obteniendo +4 CA. Si el enemigo falla, pierde su DES a CA.", "description_en": "Bait attacks of opportunity gaining +4 AC. If the enemy misses, they lose DEX to AC." },
  { "id": "pericia_combate",          "name": "Pericia en Combate",            "name_en": "Combat Expertise",            "category": "Maniobras",          "category_en": "Maneuvers",       "type": "cbt",    "prerequisites": "INT 13",                                                         "prerequisites_en": "INT 13",                                                         "description": "+1 CA de esquiva (escala +1 cada 4 BAB). -1 a ataques y maniobras (escala igual).", "description_en": "+1 dodge AC (scales +1 per 4 BAB). -1 to attacks and maneuvers (scales equally)." },
  { "id": "desarme_mejorado",         "name": "Desarme Mejorado",              "name_en": "Improved Disarm",             "category": "Maniobras",          "category_en": "Maneuvers",       "type": "cbt",    "prerequisites": "INT 13, Pericia en Combate",                                     "prerequisites_en": "INT 13, Combat Expertise",                                       "description": "+2 a BMC para desarmar, sin ataque de oportunidad. +2 a DMC contra desarme.", "description_en": "+2 to CMB for disarming, no attack of opportunity. +2 to CMD against disarm." },
  { "id": "desarme_mayor",            "name": "Desarme Mayor",                 "name_en": "Greater Disarm",              "category": "Maniobras",          "category_en": "Maneuvers",       "type": "cbt",    "prerequisites": "INT 13, Pericia en Combate, Desarme Mejorado, BAB +6",           "prerequisites_en": "INT 13, Combat Expertise, Improved Disarm, BAB +6",              "description": "+2 adicional a BMC de desarme. El arma sale 15 pies en dirección aleatoria.", "description_en": "Additional +2 to disarm CMB. The weapon flies 15 feet in a random direction." },
  { "id": "derribo_mejorado",         "name": "Derribo Mejorado",              "name_en": "Improved Trip",               "category": "Maniobras",          "category_en": "Maneuvers",       "type": "cbt",    "prerequisites": "Pericia en Combate",                                             "prerequisites_en": "Combat Expertise",                                               "description": "+2 a BMC de derribo. No provoca ataques de oportunidad al intentarlo.", "description_en": "+2 to trip CMB. Does not provoke attacks of opportunity." },
  { "id": "derribo_mayor",            "name": "Derribo Mayor",                 "name_en": "Greater Trip",                "category": "Maniobras",          "category_en": "Maneuvers",       "type": "cbt",    "prerequisites": "Pericia en Combate, Derribo Mejorado, BAB +6",                   "prerequisites_en": "Combat Expertise, Improved Trip, BAB +6",                        "description": "Los enemigos derribados provocan ataques de oportunidad inmediatos de todos los aliados amenazantes.", "description_en": "Tripped enemies provoke immediate attacks of opportunity from all threatening allies." },
  { "id": "embestida_mejorada",       "name": "Embestida Mejorada",            "name_en": "Improved Bull Rush",          "category": "Maniobras",          "category_en": "Maneuvers",       "type": "cbt",    "prerequisites": "FUE 13, Ataque Poderoso",                                        "prerequisites_en": "STR 13, Power Attack",                                           "description": "+2 a BMC para embestir. No provoca ataques de oportunidad.", "description_en": "+2 to bull rush CMB. Does not provoke attacks of opportunity." },
  { "id": "embestida_mayor",          "name": "Embestida Mayor",               "name_en": "Greater Bull Rush",           "category": "Maniobras",          "category_en": "Maneuvers",       "type": "cbt",    "prerequisites": "Ataque Poderoso, Embestida Mejorada, BAB +6",                    "prerequisites_en": "Power Attack, Improved Bull Rush, BAB +6",                       "description": "El enemigo empujado provoca ataques de oportunidad al moverse involuntariamente.", "description_en": "The pushed enemy provokes attacks of opportunity from its forced movement." },
  { "id": "arrollar_mejorado",        "name": "Arrollar Mejorado",             "name_en": "Improved Overrun",            "category": "Maniobras",          "category_en": "Maneuvers",       "type": "cbt",    "prerequisites": "Ataque Poderoso",                                                "prerequisites_en": "Power Attack",                                                   "description": "+2 a BMC arrollar. Sin ataques de oportunidad. El oponente no puede elegir evadir.", "description_en": "+2 to overrun CMB. No attacks of opportunity. Opponent cannot choose to avoid." },
  { "id": "finta_mejorada",           "name": "Finta Mejorada",                "name_en": "Improved Feint",              "category": "Engaños",            "category_en": "Feints",          "type": "cbt",    "prerequisites": "Pericia en Combate",                                             "prerequisites_en": "Combat Expertise",                                               "description": "Permite fintar como acción de movimiento en vez de acción estándar.", "description_en": "Allows you to feint as a move action instead of a standard action." },
  { "id": "finta_mayor",              "name": "Finta Mayor",                   "name_en": "Greater Feint",               "category": "Engaños",            "category_en": "Feints",          "type": "cbt",    "prerequisites": "Pericia en Combate, Finta Mejorada, BAB +6, INT 13",             "prerequisites_en": "Combat Expertise, Improved Feint, BAB +6, INT 13",               "description": "Si la finta tiene éxito, el objetivo pierde DES a la CA durante un asalto completo.", "description_en": "If the feint succeeds, the target loses DEX to AC for a full round." },
  { "id": "fintas_tacticas",          "name": "Fintas Tácticas",               "name_en": "Tactical Feints",             "category": "Engaños",            "category_en": "Feints",          "type": "cbt",    "prerequisites": "Engaños, Actuación",                                             "prerequisites_en": "Bluff, Perform",                                                 "description": "Simula vulnerabilidad para que el enemigo pierda su DES a CA al atacar.", "description_en": "Feigns vulnerability so the enemy loses DEX to AC when attacking." },
  { "id": "esquiva",                  "name": "Esquiva",                       "name_en": "Dodge",                       "category": "General",            "category_en": "General",         "type": "normal", "prerequisites": "DES 13",                                                         "prerequisites_en": "DEX 13",                                                         "description": "+1 permanente a la CA de esquiva.", "description_en": "Permanent +1 dodge bonus to AC." },
  { "id": "movilidad",                "name": "Movilidad",                     "name_en": "Mobility",                    "category": "General",            "category_en": "General",         "type": "normal", "prerequisites": "DES 13, Esquiva",                                                "prerequisites_en": "DEX 13, Dodge",                                                  "description": "+4 a CA de esquiva específicamente contra ataques de oportunidad por movimiento.", "description_en": "+4 dodge AC specifically against attacks of opportunity from movement." },
  { "id": "ataque_elastico",          "name": "Ataque Elástico",               "name_en": "Spring Attack",               "category": "Combate",            "category_en": "Combat",          "type": "cbt",    "prerequisites": "DES 13, Movilidad, Esquiva, BAB +4",                             "prerequisites_en": "DEX 13, Mobility, Dodge, BAB +4",                                "description": "Mover, atacar y seguir moviéndose sin provocar ataques de oportunidad del blanco atacado.", "description_en": "Move, attack, and continue moving without provoking attacks of opportunity from the target." },
  { "id": "ataque_torbellino",        "name": "Ataque de Torbellino",          "name_en": "Whirlwind Attack",            "category": "Combate",            "category_en": "Combat",          "type": "cbt",    "prerequisites": "DES 13, INT 13, Pericia en Combate, Esquiva, Movilidad, Ataque Elástico, BAB +4", "prerequisites_en": "DEX 13, INT 13, Combat Expertise, Dodge, Mobility, Spring Attack, BAB +4", "description": "Ataque cuerpo a cuerpo a todos los enemigos al alcance con BAB máximo. Anula ataques extras de conjuros/dotes.", "description_en": "Melee attack against all enemies within reach at full BAB. Negates extra attacks from spells/feats." },
  { "id": "reflejos_combate",         "name": "Reflejos de Combate",           "name_en": "Combat Reflexes",             "category": "Combate",            "category_en": "Combat",          "type": "cbt",    "prerequisites": "Ninguno",                                                        "prerequisites_en": "None",                                                           "description": "Ataques de oportunidad extras por asalto = mod. DES. Se pueden realizar desprevenido.", "description_en": "Extra attacks of opportunity per round = DEX mod. Can be made while flat-footed." },
  { "id": "moverse_viento",           "name": "Moverse como el Viento",        "name_en": "Wind Stance",                 "category": "Combate",            "category_en": "Combat",          "type": "cbt",    "prerequisites": "DES 15, Esquiva, BAB +6",                                        "prerequisites_en": "DEX 15, Dodge, BAB +6",                                          "description": "Mover 10 pies otorga 20% de ocultación contra ataques a distancia durante 1 asalto.", "description_en": "Moving 10 feet grants 20% concealment against ranged attacks for 1 round." },
  { "id": "moverse_rayo",             "name": "Moverse como el Rayo",          "name_en": "Lightning Stance",            "category": "Combate",            "category_en": "Combat",          "type": "cbt",    "prerequisites": "DES 17, Esquiva, Moverse como el Viento, BAB +11",               "prerequisites_en": "DEX 17, Dodge, Wind Stance, BAB +11",                            "description": "Dos acciones de movimiento otorgan 50% de probabilidad de fallo durante 1 asalto.", "description_en": "Two move actions grant 50% miss chance for 1 round." },
  { "id": "reduccion_rechazo",        "name": "Reducción y Rechazo",           "name_en": "Deflect Arrows / Repel",      "category": "Combate",            "category_en": "Combat",          "type": "cbt",    "prerequisites": "FUE 13, RD, Embestida Mejorada, Ataque Poderoso, BAB +1",        "prerequisites_en": "STR 13, DR, Improved Bull Rush, Power Attack, BAB +1",           "description": "Acción inmediata para embestir al atacante si su golpe no penetra la RD.", "description_en": "Immediate action to bull rush an attacker whose blow fails to penetrate DR." },
  { "id": "apresador_rapido",         "name": "Apresador Rápido",              "name_en": "Rapid Grappler",              "category": "Combate",            "category_en": "Combat",          "type": "cbt",    "prerequisites": "—",                                                              "prerequisites_en": "—",                                                              "description": "Mejora la eficacia y velocidad de forcejeo y apresamiento.", "description_en": "Improves efficiency and speed of grappling." },
  { "id": "engaños_red",              "name": "Engaños con la Red",            "name_en": "Net Trickery",                "category": "Combate",            "category_en": "Combat",          "type": "cbt",    "prerequisites": "Comp. red, Experto redes, Maniobras red, BAB +6",                "prerequisites_en": "Net Proficiency, Net Expert, Net Maneuvers, BAB +6",             "description": "Sustituye ataques para cegar o derribar. +2 a embestir a presas entrelazadas.", "description_en": "Trade attacks to blind or trip. +2 to bull rush entangled prey." },
  { "id": "ataque_galope",            "name": "Ataque al Galope",              "name_en": "Ride-By Attack",              "category": "Combate montado",    "category_en": "Mounted Combat", "type": "cbt",    "prerequisites": "Montar 1 rango, Combatir desde montura",                         "prerequisites_en": "Ride 1 rank, Mounted Combat",                                    "description": "Cargar montado y continuar en línea recta sin provocar ataques de oportunidad del blanco.", "description_en": "Charge while mounted and continue in a straight line without provoking attacks of opportunity from the target." },
  { "id": "carga_impetuosa",          "name": "Carga Impetuosa",               "name_en": "Spirited Charge",             "category": "Combate montado",    "category_en": "Mounted Combat", "type": "cbt",    "prerequisites": "Ataque al Galope, Combatir desde montura",                       "prerequisites_en": "Ride-By Attack, Mounted Combat",                                 "description": "Duplica el daño al cargar montado (triplica con lanza de caballería).", "description_en": "Doubles damage when charging mounted (triples with a lance)." },
  { "id": "arrollar_trample",         "name": "Arrollar (Trample)",            "name_en": "Trample",                     "category": "Combate montado",    "category_en": "Mounted Combat", "type": "cbt",    "prerequisites": "Combatir desde montura",                                         "prerequisites_en": "Mounted Combat",                                                 "description": "Arrollar mientras cabalgas; los blancos no pueden evadir sin consecuencias.", "description_en": "Overrun while mounted; targets cannot avoid without consequences." },
  { "id": "acrobacias_montadas",      "name": "Acrobacias Montadas",           "name_en": "Mounted Acrobatics",          "category": "Combate montado",    "category_en": "Mounted Combat", "type": "cbt",    "prerequisites": "—",                                                              "prerequisites_en": "—",                                                              "description": "Potencia las pruebas acrobáticas realizadas sobre la montura.", "description_en": "Enhances acrobatic checks performed while mounted." },
  { "id": "dureza",                   "name": "Dureza",                        "name_en": "Toughness",                   "category": "General",            "category_en": "General",         "type": "normal", "prerequisites": "Ninguno",                                                        "prerequisites_en": "None",                                                           "description": "+3 PG permanentes. Por cada DG extra de nivel 4 en adelante, +1 PG adicional.", "description_en": "+3 permanent HP. For each HD beyond level 3, +1 additional HP." },
  { "id": "duro_pelar",               "name": "Duro de Pelar",                 "name_en": "Diehard",                     "category": "General",            "category_en": "General",         "type": "normal", "prerequisites": "Aguante",                                                        "prerequisites_en": "Endurance",                                                      "description": "Estabilización automática bajo 0 PG. Puede actuar sufriendo 1 daño/asalto.", "description_en": "Automatic stabilization below 0 HP. Can act while taking 1 damage/round." },
  { "id": "aguante",                  "name": "Aguante",                       "name_en": "Endurance",                   "category": "General",            "category_en": "General",         "type": "normal", "prerequisites": "Ninguno",                                                        "prerequisites_en": "None",                                                           "description": "+4 a salvaciones contra fatiga, clima, hambre. Dormir con armadura ligera/media sin fatiga.", "description_en": "+4 to saves against fatigue, weather, and hunger. Sleep in light/medium armor without fatigue." },
  { "id": "gran_fortaleza",           "name": "Gran Fortaleza",                "name_en": "Great Fortitude",             "category": "General",            "category_en": "General",         "type": "normal", "prerequisites": "Ninguno",                                                        "prerequisites_en": "None",                                                           "description": "+2 fijo a tiradas de salvación de Fortaleza.", "description_en": "Flat +2 to Fortitude saves." },
  { "id": "reflejos_rapidos",         "name": "Reflejos Rápidos",              "name_en": "Lightning Reflexes",          "category": "General",            "category_en": "General",         "type": "normal", "prerequisites": "Ninguno",                                                        "prerequisites_en": "None",                                                           "description": "+2 fijo a tiradas de salvación de Reflejos.", "description_en": "Flat +2 to Reflex saves." },
  { "id": "voluntad_hierro",          "name": "Voluntad de Hierro",            "name_en": "Iron Will",                   "category": "General",            "category_en": "General",         "type": "normal", "prerequisites": "Ninguno",                                                        "prerequisites_en": "None",                                                           "description": "+2 fijo a tiradas de salvación de Voluntad.", "description_en": "Flat +2 to Will saves." },
  { "id": "gran_fortaleza_mejorada",  "name": "Gran Fortaleza Mejorada",       "name_en": "Improved Great Fortitude",    "category": "General",            "category_en": "General",         "type": "normal", "prerequisites": "Gran Fortaleza",                                                 "prerequisites_en": "Great Fortitude",                                                "description": "Permite repetir 1 tirada de salvación de Fortaleza 1 vez/día.", "description_en": "Reroll 1 Fortitude save 1/day." },
  { "id": "reflejos_rapidos_mej",     "name": "Reflejos Rápidos Mejorados",    "name_en": "Improved Lightning Reflexes", "category": "General",            "category_en": "General",         "type": "normal", "prerequisites": "Reflejos Rápidos",                                               "prerequisites_en": "Lightning Reflexes",                                             "description": "Permite repetir 1 tirada de salvación de Reflejos 1 vez/día.", "description_en": "Reroll 1 Reflex save 1/day." },
  { "id": "alerta",                   "name": "Alerta",                        "name_en": "Alertness",                   "category": "General",            "category_en": "General",         "type": "normal", "prerequisites": "Ninguno",                                                        "prerequisites_en": "None",                                                           "description": "+2 a Percepción y Averiguar intenciones (+4 con 10 rangos en la habilidad).", "description_en": "+2 to Perception and Sense Motive (+4 with 10 ranks in the skill)." },
  { "id": "iniciativa_mejorada",      "name": "Iniciativa Mejorada",           "name_en": "Improved Initiative",         "category": "General",            "category_en": "General",         "type": "normal", "prerequisites": "Ninguno",                                                        "prerequisites_en": "None",                                                           "description": "+4 a todas las tiradas de Iniciativa.", "description_en": "+4 to all Initiative rolls." },
  { "id": "soltura_habilidad",        "name": "Soltura con una Habilidad",     "name_en": "Skill Focus",                 "category": "General",            "category_en": "General",         "type": "normal", "prerequisites": "Ninguno",                                                        "prerequisites_en": "None",                                                           "description": "+3 a todas las pruebas de la habilidad elegida (+6 con 10 rangos).", "description_en": "+3 to all checks with the chosen skill (+6 with 10 ranks)." },
  { "id": "alma_acero",               "name": "Alma de Acero",                 "name_en": "Steel Soul",                  "category": "Racial",             "category_en": "Racial",          "type": "normal", "prerequisites": "Enano, rasgo Resistente",                                        "prerequisites_en": "Dwarf, Hardy racial trait",                                      "description": "+4 (en vez de +2) a salvaciones contra conjuros y efectos mágicos.", "description_en": "+4 (instead of +2) to saves against spells and magical effects." },
  { "id": "acrobatico",               "name": "Acrobático",                    "name_en": "Acrobatic",                   "category": "General",            "category_en": "General",         "type": "normal", "prerequisites": "Ninguno",                                                        "prerequisites_en": "None",                                                           "description": "+2 a Acrobacias y Volar (+4 con 10 rangos).", "description_en": "+2 to Acrobatics and Fly (+4 with 10 ranks)." },
  { "id": "afinidad_animales",        "name": "Afinidad con los Animales",     "name_en": "Animal Affinity",             "category": "General",            "category_en": "General",         "type": "normal", "prerequisites": "Ninguno",                                                        "prerequisites_en": "None",                                                           "description": "+2 a Trato con animales y Montar (+4 con 10 rangos).", "description_en": "+2 to Handle Animal and Ride (+4 with 10 ranks)." },
  { "id": "conjurar_combate",         "name": "Conjurar en Combate",           "name_en": "Combat Casting",              "category": "Magia",              "category_en": "Magic",           "type": "normal", "prerequisites": "Aptitud para lanzar conjuros",                                   "prerequisites_en": "Ability to cast spells",                                         "description": "+4 a pruebas de Concentración al conjurar a la defensiva o apresado.", "description_en": "+4 to Concentration checks when casting defensively or grappled." },
  { "id": "soltura_conjuros",         "name": "Soltura con los Conjuros",      "name_en": "Spell Focus",                 "category": "Magia",              "category_en": "Magic",           "type": "normal", "prerequisites": "Aptitud para lanzar conjuros",                                   "prerequisites_en": "Ability to cast spells",                                         "description": "+1 a la CD de las salvaciones de la escuela de magia elegida.", "description_en": "+1 to saving throw DCs of the chosen school of magic." },
  { "id": "soltura_mayor_conjuros",   "name": "Soltura Mayor con los Conjuros","name_en": "Greater Spell Focus",         "category": "Magia",              "category_en": "Magic",           "type": "normal", "prerequisites": "Soltura con los Conjuros",                                       "prerequisites_en": "Spell Focus",                                                    "description": "+1 adicional a la CD (acumulable, total +2 sobre la base).", "description_en": "Additional +1 to DC (stacks, total +2 over base)." },
  { "id": "abstencion_materiales",    "name": "Abstención de Materiales",      "name_en": "Eschew Materials",            "category": "Magia",              "category_en": "Magic",           "type": "normal", "prerequisites": "Ninguno",                                                        "prerequisites_en": "None",                                                           "description": "Permite lanzar conjuros ignorando componentes materiales de coste ≤1 mo.", "description_en": "Cast spells ignoring material components costing 1 gp or less." },
  { "id": "golpe_arcano",             "name": "Golpe Arcano",                  "name_en": "Arcane Strike",               "category": "Magia",              "category_en": "Magic",           "type": "cbt",    "prerequisites": "Aptitud para lanzar conjuros arcanos",                           "prerequisites_en": "Ability to cast arcane spells",                                  "description": "Acción rápida: +1 al daño del arma y la convierte en mágica frente a RD ese turno.", "description_en": "Swift action: +1 to weapon damage and treat it as magical against DR that turn." },
  { "id": "maestria_conjuros",        "name": "Maestría en Conjuros",          "name_en": "Spell Mastery",               "category": "Magia",              "category_en": "Magic",           "type": "normal", "prerequisites": "Mago nivel 1",                                                   "prerequisites_en": "Wizard level 1",                                                 "description": "Permite preparar un conjunto de hechizos clave sin necesitar el libro de conjuros.", "description_en": "Prepare a set of chosen spells without needing the spellbook." },
  { "id": "disipacion_destructiva",   "name": "Disipación Destructiva",        "name_en": "Disruptive Dispel",           "category": "Magia",              "category_en": "Magic",           "type": "normal", "prerequisites": "Nivel lanzador 11, Disipar Magia",                               "prerequisites_en": "Caster level 11, Dispel Magic",                                  "description": "Al disipar con éxito, el objetivo queda aturdido 1 asalto (o indispuesto si supera la salvación).", "description_en": "On a successful dispel, target is dazed 1 round (or sickened on a successful save)." },
  { "id": "estallido_arcano",         "name": "Estallido Arcano",              "name_en": "Arcane Burst",                "category": "Magia",              "category_en": "Magic",           "type": "normal", "prerequisites": "Nivel de lanzador 10",                                           "prerequisites_en": "Caster level 10",                                                "description": "Sacrifica un hechizo preparado para disparar un rayo de daño.", "description_en": "Sacrifice a prepared spell to fire a damaging ray." },
  { "id": "arcanos_extendidos",       "name": "Arcanos Extendidos",            "name_en": "Extra Arcana",                "category": "Magia",              "category_en": "Magic",           "type": "normal", "prerequisites": "Aptitud Bardo o Hechicero",                                      "prerequisites_en": "Bard or Sorcerer casting",                                       "description": "Añade un conjuro nuevo a la lista de conjuros conocidos de forma permanente.", "description_en": "Permanently add a new spell to your known spells list." },
  { "id": "conjuros_perforantes",     "name": "Conjuros Perforantes",          "name_en": "Spell Penetration",           "category": "Metamagia",          "category_en": "Metamagic",       "type": "meta",   "prerequisites": "—",                                                              "prerequisites_en": "—",                                                              "description": "Bonificadores de penetración a las pruebas para superar Resistencia a la Magia.", "description_en": "Penetration bonuses on checks to overcome Spell Resistance." },
  { "id": "canalizacion_rapida",      "name": "Canalización Rápida",           "name_en": "Quick Channel",               "category": "Divina",             "category_en": "Divine",          "type": "normal", "prerequisites": "Saber (religión) 5, Canalizar Energía",                          "prerequisites_en": "Knowledge (religion) 5, Channel Energy",                         "description": "Permite canalizar como acción de movimiento. Consume 2 usos diarios.", "description_en": "Channel as a move action. Consumes 2 daily uses." },
  { "id": "canalizacion_selectiva",   "name": "Canalización Selectiva",        "name_en": "Selective Channeling",        "category": "Divina",             "category_en": "Divine",          "type": "normal", "prerequisites": "CAR 13, Canalizar Energía",                                      "prerequisites_en": "CHA 13, Channel Energy",                                         "description": "Excluye hasta (mod. CAR) objetivos del área de canalización.", "description_en": "Exclude up to (CHA mod) targets from the channel's area." },
  { "id": "canalizacion_mejorada",    "name": "Canalización Mejorada",         "name_en": "Improved Channel",            "category": "Divina",             "category_en": "Divine",          "type": "normal", "prerequisites": "Canalizar Energía",                                              "prerequisites_en": "Channel Energy",                                                 "description": "+2 a la CD para resistir la canalización dañina.", "description_en": "+2 to the DC to resist harmful channeling." },
  { "id": "canalizar_castigo",        "name": "Canalizar Castigo",             "name_en": "Channel Smite",               "category": "Divina",             "category_en": "Divine",          "type": "normal", "prerequisites": "Canalizar Energía",                                              "prerequisites_en": "Channel Energy",                                                 "description": "Acción rápida: incorpora 1 uso de canalización a un ataque cuerpo a cuerpo.", "description_en": "Swift action: add 1 channel use to a melee attack." },
  { "id": "canalizador_versatil",     "name": "Canalizador Versátil",          "name_en": "Versatile Channeler",         "category": "Divina",             "category_en": "Divine",          "type": "normal", "prerequisites": "Clérigo Neutral, Canalizar Energía",                             "prerequisites_en": "Neutral Cleric, Channel Energy",                                 "description": "Puede canalizar positiva y negativa. La opuesta funciona a nivel de clérigo -2.", "description_en": "Channel both positive and negative. The opposite works at cleric level -2." },
  { "id": "comandar_muertos",         "name": "Comandar Muertos Vivientes",    "name_en": "Command Undead",              "category": "Divina",             "category_en": "Divine",          "type": "normal", "prerequisites": "Canalizar Energía negativa",                                     "prerequisites_en": "Channel negative energy",                                        "description": "Usa la canalización para obligar a no-muertos a obedecer.", "description_en": "Use channel energy to command undead to obey." },
  { "id": "apresurar_conjuro",        "name": "Apresurar Conjuro",             "name_en": "Quicken Spell",               "category": "Metamagia",          "category_en": "Metamagic",       "type": "meta",   "prerequisites": "—",                                                              "prerequisites_en": "—",                                                              "description": "El conjuro se lanza como Acción Rápida. Ocupa un slot +4 niveles superior.", "description_en": "Cast the spell as a swift action. Uses a slot +4 levels higher." },
  { "id": "maximizar_conjuro",        "name": "Maximizar Conjuro",             "name_en": "Maximize Spell",              "category": "Metamagia",          "category_en": "Metamagic",       "type": "meta",   "prerequisites": "—",                                                              "prerequisites_en": "—",                                                              "description": "Todos los efectos numéricos de dados dan el valor máximo garantizado. +3 niveles de slot.", "description_en": "All variable numeric effects yield maximum value. +3 spell slot levels." },
  { "id": "potenciar_conjuro",        "name": "Potenciar Conjuro",             "name_en": "Empower Spell",               "category": "Metamagia",          "category_en": "Metamagic",       "type": "meta",   "prerequisites": "—",                                                              "prerequisites_en": "—",                                                              "description": "+50% a todos los resultados numéricos variables del conjuro. +2 niveles de slot.", "description_en": "+50% to all variable numeric results of the spell. +2 spell slot levels." },
  { "id": "prolongar_conjuro",        "name": "Prolongar Conjuro",             "name_en": "Extend Spell",                "category": "Metamagia",          "category_en": "Metamagic",       "type": "meta",   "prerequisites": "—",                                                              "prerequisites_en": "—",                                                              "description": "Duplica la duración del conjuro. +1 nivel de slot.", "description_en": "Doubles spell duration. +1 spell slot level." },
  { "id": "intensificar_conjuro",     "name": "Intensificar Conjuro",          "name_en": "Heighten Spell",              "category": "Metamagia",          "category_en": "Metamagic",       "type": "meta",   "prerequisites": "—",                                                              "prerequisites_en": "—",                                                              "description": "Aumenta la CD para resistir el conjuro. +1 nivel de slot.", "description_en": "Increases the DC to resist the spell. +1 spell slot level." },
  { "id": "ampliar_conjuro",          "name": "Ampliar Conjuro",               "name_en": "Enlarge Spell",               "category": "Metamagia",          "category_en": "Metamagic",       "type": "meta",   "prerequisites": "—",                                                              "prerequisites_en": "—",                                                              "description": "Duplica distancias, radios y áreas del conjuro. +1 nivel de slot.", "description_en": "Doubles ranges, radii, and areas of the spell. +1 spell slot level." },
  { "id": "conjurar_sin_moverse",     "name": "Conjurar sin Moverse",          "name_en": "Still Spell",                 "category": "Metamagia",          "category_en": "Metamagic",       "type": "meta",   "prerequisites": "—",                                                              "prerequisites_en": "—",                                                              "description": "Elimina los componentes somáticos del conjuro. Penalizador al slot.", "description_en": "Removes somatic components of the spell. Slot penalty." },
  { "id": "conjurar_silencio",        "name": "Conjurar en Silencio",          "name_en": "Silent Spell",                "category": "Metamagia",          "category_en": "Metamagic",       "type": "meta",   "prerequisites": "—",                                                              "prerequisites_en": "—",                                                              "description": "Elimina los componentes verbales del conjuro. Penalizador al slot.", "description_en": "Removes verbal components of the spell. Slot penalty." },
  { "id": "elaborar_pocion",          "name": "Elaborar Poción",               "name_en": "Brew Potion",                 "category": "Creación",           "category_en": "Crafting",        "type": "normal", "prerequisites": "Nivel de lanzador 3",                                            "prerequisites_en": "Caster level 3",                                                 "description": "Elabora pociones (hasta hechizos de nivel 3) por el 50% de su coste tasado.", "description_en": "Brew potions (up to level 3 spells) for 50% of their assessed cost." },
  { "id": "fabricar_armas",           "name": "Fabricar Armas y Armaduras",    "name_en": "Craft Magic Arms and Armor",  "category": "Creación",           "category_en": "Crafting",        "type": "normal", "prerequisites": "Nivel de lanzador 5",                                            "prerequisites_en": "Caster level 5",                                                 "description": "Crea armas/armaduras mágicas +1 a +5 con efectos exóticos, invirtiendo el 50% del valor.", "description_en": "Create magic weapons/armor +1 to +5 with exotic effects, investing 50% of the value." },
  { "id": "fabricar_maravilloso",     "name": "Fabricar Objeto Maravilloso",   "name_en": "Craft Wondrous Item",         "category": "Creación",           "category_en": "Crafting",        "type": "normal", "prerequisites": "Nivel de lanzador 3",                                            "prerequisites_en": "Caster level 3",                                                 "description": "Manufactura complementos mágicos (cinturones, botas…) por el 50% del valor base.", "description_en": "Craft magic accessories (belts, boots...) for 50% of base value." },
  { "id": "fabricar_varita",          "name": "Fabricar Varita",               "name_en": "Craft Wand",                  "category": "Creación",           "category_en": "Crafting",        "type": "normal", "prerequisites": "Nivel de lanzador 5",                                            "prerequisites_en": "Caster level 5",                                                 "description": "Elabora varitas (hasta conjuros de nivel 4, 50 cargas) por el 50% del coste.", "description_en": "Craft wands (up to level 4 spells, 50 charges) for 50% of the cost." },
  { "id": "forjar_anillo",            "name": "Forjar Anillo",                 "name_en": "Forge Ring",                  "category": "Creación",           "category_en": "Crafting",        "type": "normal", "prerequisites": "Nivel de lanzador 7",                                            "prerequisites_en": "Caster level 7",                                                 "description": "Manufactura anillos mágicos invirtiendo el 50% de su valor en materiales y tiempo.", "description_en": "Craft magic rings investing 50% of their value in materials and time." },
  { "id": "inscribir_pergamino",      "name": "Inscribir Pergamino",           "name_en": "Scribe Scroll",               "category": "Creación",           "category_en": "Crafting",        "type": "normal", "prerequisites": "Nivel de lanzador 1",                                            "prerequisites_en": "Caster level 1",                                                 "description": "Crea pergaminos de un uso por el 50% del coste comercial del conjuro.", "description_en": "Create single-use scrolls for 50% of the commercial cost of the spell." },
  { "id": "fabricar_baston",          "name": "Fabricar Bastón / Cetro",       "name_en": "Craft Staff / Rod",           "category": "Creación",           "category_en": "Crafting",        "type": "normal", "prerequisites": "Nivel de lanzador avanzado",                                     "prerequisites_en": "Advanced caster level",                                          "description": "Crea bastones con 10 cargas de conjuros de alto nivel por el 50% del coste.", "description_en": "Craft staves with 10 charges of high-level spells for 50% of the cost." },
  { "id": "estilo_grulla",            "name": "Estilo de la Grulla",           "name_en": "Crane Style",                 "category": "Estilos de combate", "category_en": "Combat Styles",   "type": "cbt",    "prerequisites": "Esquiva, Golpe sin Armas Mejorado, BAB +2 o Monje 1",            "prerequisites_en": "Dodge, Improved Unarmed Strike, BAB +2 or Monk 1",               "description": "Reduce el penalizador por luchar a la defensiva a -2. +1 CA de esquiva pasiva.", "description_en": "Reduces the fighting defensively penalty to -2. +1 passive dodge AC." },
  { "id": "estilo_mantis",            "name": "Estilo de la Mantis",           "name_en": "Mantis Style",                "category": "Estilos de combate", "category_en": "Combat Styles",   "type": "cbt",    "prerequisites": "Golpe sin Armas Mejorado",                                       "prerequisites_en": "Improved Unarmed Strike",                                        "description": "Optimiza intentos de Puñetazo Aturdidor apuntando a puntos vitales.", "description_en": "Optimizes Stunning Fist attempts by targeting vital points." },
  { "id": "estilo_pantera",           "name": "Estilo de la Pantera",          "name_en": "Panther Style",               "category": "Estilos de combate", "category_en": "Combat Styles",   "type": "cbt",    "prerequisites": "SAB 13, Golpe sin Armas",                                        "prerequisites_en": "WIS 13, Unarmed Strike",                                         "description": "Represalias automáticas masivas frente a quien cometa ataques de oportunidad contra ti.", "description_en": "Automatic mass retaliation against anyone making attacks of opportunity on you." },
  { "id": "estilo_serpiente",         "name": "Estilo de la Serpiente",        "name_en": "Snake Style",                 "category": "Estilos de combate", "category_en": "Combat Styles",   "type": "cbt",    "prerequisites": "Golpe sin Armas Mejorado, Acrobacias",                           "prerequisites_en": "Improved Unarmed Strike, Acrobatics",                            "description": "Fintas y contraataques eficaces cuando el personaje está en inferioridad numérica.", "description_en": "Effective feints and counterattacks when the character is outnumbered." },
  { "id": "estilo_ifriti",            "name": "Estilo del Ifriti / Shaitan",   "name_en": "Ifrit / Shaitan Style",       "category": "Estilos de combate", "category_en": "Combat Styles",   "type": "cbt",    "prerequisites": "Dominio Desvío, afinidad elemental",                             "prerequisites_en": "Deflecting Mastery, elemental affinity",                         "description": "Ifriti: añade daño de fuego orgánico. Shaitan: añade daño ácido y disuelve armaduras.", "description_en": "Ifrit: adds organic fire damage. Shaitan: adds acid damage and dissolves armor." },
  { "id": "estilo_kirin",             "name": "Estilo del Kirin",              "name_en": "Kirin Style",                 "category": "Estilos de combate", "category_en": "Combat Styles",   "type": "cbt",    "prerequisites": "Conocimiento arcano o erudito, pericia monástica",               "prerequisites_en": "Arcane or scholarly Knowledge, monastic expertise",              "description": "Análisis esotérico del enemigo para infligir daño exacto con ventajas analíticas perimetrales.", "description_en": "Esoteric analysis of the enemy to inflict precise damage with perimeter analytical advantages." },
  { "id": "critico_incapacitante",    "name": "Crítico Incapacitante",         "name_en": "Staggering Critical",         "category": "Críticos",           "category_en": "Critical",        "type": "crit",   "prerequisites": "Crítico Mejorado, BAB +11",                                      "prerequisites_en": "Improved Critical, BAB +11",                                     "description": "Un golpe crítico reduce la agilidad del objetivo e induce lisiadura motriz persistente.", "description_en": "A critical hit reduces the target's agility and induces persistent motor impairment." },
  { "id": "critico_sangrante",        "name": "Crítico Sangrante",             "name_en": "Bleeding Critical",           "category": "Críticos",           "category_en": "Critical",        "type": "crit",   "prerequisites": "Crítico Mejorado, BAB alto",                                     "prerequisites_en": "Improved Critical, high BAB",                                    "description": "Un golpe crítico causa 1d6+ daño por desangrado cada asalto hasta que se trate.", "description_en": "A critical hit causes 1d6+ bleed damage each round until treated." },
  { "id": "critico_aturdidor",        "name": "Crítico Aturdidor",             "name_en": "Stunning Critical",           "category": "Críticos",           "category_en": "Critical",        "type": "crit",   "prerequisites": "BAB +15",                                                        "prerequisites_en": "BAB +15",                                                        "description": "Un golpe crítico impone Aturdido: pierde turno, defensas y suelta armas.", "description_en": "A critical hit imposes Stunned: loses turn, defenses, and drops weapons." },
  { "id": "critico_azotador",         "name": "Crítico Azotador",              "name_en": "Sickening Critical",          "category": "Críticos",           "category_en": "Critical",        "type": "crit",   "prerequisites": "Nivel de lanzador 5",                                            "prerequisites_en": "Caster level 5",                                                 "description": "Un golpe crítico infecta con Azote Menor, dañando los atributos del objetivo.", "description_en": "A critical hit infects with Lesser Blight, damaging the target's ability scores." },
  { "id": "critico_agotador",         "name": "Crítico Agotador / Cegador",    "name_en": "Tiring / Blinding Critical",  "category": "Críticos",           "category_en": "Critical",        "type": "crit",   "prerequisites": "BAB elevado (según variante)",                                   "prerequisites_en": "High BAB (varies by variant)",                                   "description": "Un golpe crítico impone Fatigado, Cegado, Sordo o Nauseado según la variante.", "description_en": "A critical hit imposes Fatigued, Blinded, Deafened, or Nauseated depending on the variant." },
  { "id": "flanqueo_grupo",           "name": "Flanqueo en Grupo",             "name_en": "Outflank",                    "category": "Trabajo en equipo",  "category_en": "Teamwork",        "type": "team",   "prerequisites": "Dote base, aliado adyacente compatible",                         "prerequisites_en": "Base feat, compatible adjacent ally",                            "description": "El bonificador base por flanquear sube de +2 a +4 al ataque.", "description_en": "The base flanking bonus increases from +2 to +4 on attack." },
  { "id": "aprovechar_momento",       "name": "Aprovechar el Momento",         "name_en": "Seize the Moment",            "category": "Trabajo en equipo",  "category_en": "Teamwork",        "type": "team",   "prerequisites": "Reflejos de Combate, aliado compatible",                         "prerequisites_en": "Combat Reflexes, compatible ally",                               "description": "Obtienes un ataque de oportunidad gratuito si un aliado logra un golpe crítico contra tu enemigo.", "description_en": "Gain a free attack of opportunity if an ally scores a critical hit against your enemy." },
  { "id": "defensa_coordinada",       "name": "Defensa Coordinada / A Cubierto","name_en": "Coordinated Defense / Shake It Off","category": "Trabajo en equipo", "category_en": "Teamwork",       "type": "team",  "prerequisites": "Adyacencia compartida",                                          "prerequisites_en": "Shared adjacency",                                               "description": "Absorbe daño de tacleo y permite usar las tiradas de Reflejos del aliado en tu lugar.", "description_en": "Absorbs tackle damage and lets you use the ally's Reflex saves in your place." },
  { "id": "ataque_manada",            "name": "Ataque en Manada / Cambiarse",  "name_en": "Pack Attack / Swap Places",   "category": "Trabajo en equipo",  "category_en": "Teamwork",        "type": "team",   "prerequisites": "Aliado en formación",                                            "prerequisites_en": "Ally in formation",                                              "description": "Intercambia casillas sin ataques de oportunidad, o suma ataques de los aliados.", "description_en": "Swap squares without attacks of opportunity, or combine allies' attacks." },
  { "id": "proezas_agallas",          "name": "Proezas de Agallas",            "name_en": "Grit Deeds",                  "category": "Combate",            "category_en": "Combat",          "type": "cbt",    "prerequisites": "Pistolero o Aficionado, Arma de fuego",                          "prerequisites_en": "Gunslinger or Amateur Gunslinger, Firearm",                      "description": "Aumenta la reserva de Agallas (Grit), permite recargas gratuitas o tiros de carambola.", "description_en": "Increases the Grit pool, allows free reloads or trick shots." },
  { "id": "truco_piedra_trueno",      "name": "Truco de Piedra de Trueno",     "name_en": "Thunderstone Trick",          "category": "Combate",            "category_en": "Combat",          "type": "cbt",    "prerequisites": "Alquimia base / Martillo",                                       "prerequisites_en": "Basic Alchemy / Hammer",                                         "description": "Al acertar, el arma detona sordera e impacto aturdidor como efecto colateral.", "description_en": "On a hit, the weapon detonates deafness and stunning impact as a side effect." },
  { "id": "maniobras_monje",          "name": "Maniobras de Monje",            "name_en": "Monk Maneuvers",              "category": "Combate",            "category_en": "Combat",          "type": "cbt",    "prerequisites": "BAB / Acrobacias / Sigilo",                                      "prerequisites_en": "BAB / Acrobatics / Stealth",                                     "description": "Saltos y apalancamientos salvajes. Apresamientos sin fisuras o asaltos de tigre.", "description_en": "Wild leaps and leverage. Seamless grapples or tiger-style assaults." },
  { "id": "maestria_armaduras",       "name": "Maestría con Armaduras",        "name_en": "Armor Mastery",               "category": "Combate",            "category_en": "Combat",          "type": "cbt",    "prerequisites": "Competencia de equipo base",                                     "prerequisites_en": "Base armor proficiency",                                         "description": "Reduce el penalizador por armadura a la DES, permitiendo acrobacias con blindajes pesados.", "description_en": "Reduces armor check penalty on DEX, allowing acrobatics with heavy armor." }
]
